aci_mcp/__init__.py
aci_mcp/__main__.py
aci_mcp/apps_server.py
aci_mcp/unified_server.py
aci_mcp/vibeops_server.py
aci_mcp/common/__init__.py
aci_mcp/common/runners.py
aci_mcp/common/validators.py
mseep_aci_mcp-1.0.8.dist-info/licenses/LICENSE
mseep_aci_mcp-1.0.8.dist-info/METADATA
mseep_aci_mcp-1.0.8.dist-info/WHEEL
mseep_aci_mcp-1.0.8.dist-info/entry_points.txt
mseep_aci_mcp-1.0.8.dist-info/top_level.txt
mseep_aci_mcp-1.0.8.dist-info/RECORD
