Metadata-Version: 2.4
Name: mseep-aci-mcp
Version: 1.0.8
Summary: ACI MCP server, built on top of ACI.dev by Aipolabs
Author-email: mseep <support@skydeck.ai>
Maintainer-email: hanyi <support@aipolabs.xyz>
Keywords: aipolabs,mcp,aci,mcp server,llm,tool calling,function calling
Classifier: Typing :: Typed
Classifier: Development Status :: 4 - Beta
Classifier: Intended Audience :: Developers
Classifier: Programming Language :: Python :: 3.10
Classifier: Programming Language :: Python :: 3.11
Classifier: Programming Language :: Python :: 3.12
Classifier: Programming Language :: Python :: 3.13
Classifier: Operating System :: OS Independent
Classifier: Operating System :: POSIX
Classifier: Operating System :: MacOS
Classifier: Operating System :: POSIX :: Linux
Classifier: Operating System :: Microsoft :: Windows
Classifier: Topic :: Software Development :: Libraries :: Python Modules
Requires-Python: >=3.10
License-File: LICENSE
Requires-Dist: aci-sdk>=1.0.0b2
Requires-Dist: anthropic>=0.49.0
Requires-Dist: anyio>=4.9.0
Requires-Dist: click>=8.1.8
Requires-Dist: httpx>=0.27.2
Requires-Dist: mcp>=1.6.0
Requires-Dist: starlette>=0.46.1
Requires-Dist: uvicorn>=0.34.0
Dynamic: license-file
